eka_mcp_server/__init__.py
eka_mcp_server/constants.py
eka_mcp_server/eka_client.py
eka_mcp_server/mcp_server.py
eka_mcp_server/models.py
eka_mcp_server/server.py
eka_mcp_server/utils.py
mseep_eka_mcp_server-0.3.2.dist-info/licenses/LICENSE
mseep_eka_mcp_server-0.3.2.dist-info/METADATA
mseep_eka_mcp_server-0.3.2.dist-info/WHEEL
mseep_eka_mcp_server-0.3.2.dist-info/entry_points.txt
mseep_eka_mcp_server-0.3.2.dist-info/top_level.txt
mseep_eka_mcp_server-0.3.2.dist-info/RECORD
